[
    {
        "appearance": [
        "       ",
        "   o   ",
        "./\\|/\\.",
        "( o.o )",
        " > ^ < "
        ],
        "name": "normal",
        "enum": "APPEARANCE_DEFAULT"
    },
    {
        "appearance": [
        "       ",
        "   o   ",
        "./\\|/\\.",
        "{(\\./)}",
        " > ^ < "
        ],
        "name": "aggreso",
        "enum": "APPEARANCE_ANGRY"
    },    
    {
        "appearance": [
        "       ",
        "   o   ",
        "./\\|/\\.",
        "( ^.^ )",
        " > ^ < "
        ],
        "name": "happier",
        "enum": "APPEARANCE_HAPPY"
    },
    {
        "appearance": [
        "   ?   ",
        " ? o ? ",
        "./\\|/\\.",
        "( 9.6 )",
        " > r < "
        ],
        "name": "confused",
        "enum": "APPEARANCE_CONFUSED"
    },
    {
        "appearance": [
        "       ",
        "   o   ",
        "./]|[\\.",
        "} o.o {",
        " > ^ < "
        ],
        "name": "mainey",
        "enum": "APPEARANCE_MAINECOON"
    },
    {
        "appearance": [
        "       ",
        "   o   ",
        "./\\|/\\.",
        "( o.^ )",
        " > u < "
        ],
        "name": "winky",
        "enum": "APPEARANCE_WINK"
    },
    {
        "appearance": [
        "       ",
        "   o   ",
        "./\\|/\\.",
        "( =,= )",
        "Zzz^ < "
        ],
        "name": "sleepy",
        "enum": "APPEARANCE_SLEEPY"
    },
    {
        "appearance": [
        "       ",
        "   o   ",
        "./\\|/\\.",
        "(_o.o_)",
        " > v < "
        ],
        "name": "blusher",
        "enum": "APPEARANCE_BLUSHED"
    },
    {
        "appearance": [
        "       ",
        "   o   ",
        "./\\|/\\.",
        "( $.$ )",
        " > u < "
        ],
        "name": "greedy",
        "enum": "APPEARANCE_MONEY"
    },
    {
        "appearance": [
        "       ",
        "   o   ",
        ".n_|_n.",
        "( o.o )",
        " > ^ < "
        ],
        "name": "folder",
        "enum": "APPEARANCE_SCOTFOLD"
    },
    {
        "appearance": [
        "       ",
        "   o   ",
        ".^,|,^.",
        "( o.o )",
        " > v < "
        ],
        "name": "tinyear",
        "enum": "APPEARANCE_SCOTFOLD"
    },
    {
        "appearance": [
        "       ",
        "   o   ",
        "./\\l/\\.",
        "( +.+ )",
        " > - < "
        ],
        "name": "wired",
        "enum": "APPEARANCE_CAFFEINE"
    },
    {
        "appearance": [
        "       ",
        "`,-*-,`",
        "`_---_`",
        "( v.v )",
        "u> ^ <n"
        ],
        "name": "monkely",
        "enum": "APPEARANCE_MONK"
    },
    {
        "appearance": [
        "       ",
        "  _*_  ",
        "./|-|\\.",
        "( @.@ )",
        "=> v <="
        ],
        "name": "devil",
        "enum": "APPEARANCE_DEVIL"
    },
    {
        "appearance": [
        "       ",
        "   V   ",
        "./\\|/\\.",
        "|\\\\|//)",
        "T> u < "
        ],
        "name": "knight",
        "enum": "APPEARANCE_KNIGHT"
    },
    {
        "appearance": [
        "       ",
        "  ,/^\\_",
        "_/___{_",
        "( o.o T",
        " > W <|"
        ],
        "name": "wizard",
        "enum": "APPEARANCE_WIZARD"
    },
    {
        "appearance": [
        "       ",
        "   o   ",
        "./\\|/\\.",
        "([o.o])",
        " > b sh"
        ],
        "name": "sneaky",
        "enum": "APPEARANCE_NINJA"
    },
    {
        "appearance": [
        "  _ _  ",
        ".' ` '.",
        "(/\\_/\\)",
        "(.oCo.)",
        " > = < "
        ],
        "name": "clowny",
        "enum": "APPEARANCE_CLOWN"
    },
    {
        "appearance": [
        "       ",
        "   .   ",
        "./\\|/\\.",
        "< 0,0 >",
        " > w < "
        ],
        "name": "Skel",
        "enum": "APPEARANCE_SKEL"
    },
    {
        "appearance": [
        "       ",
        "   o   ",
        "./\\|/\\.",
        "(#o.0 )",
        " >_C#< "
        ],
        "name": "Zombie",
        "enum": "APPEARANCE_ZOMBIE"
    },
    {
        "appearance": [
        "       ",
        "   o   ",
        "./\\|/\\.",
        "( o^o )",
        "^>' '<^"
        ],
        "name": "Vamp",
        "enum": "APPEARANCE_VAMP"
    },
    {
        "appearance": [
        "       ",
        "       ",
        " .---. ",
        "( .l. )",
        " > - < "
        ],
        "name": "human??",
        "enum": "APPEARANCE_HUMAN"
    },
    {
        "appearance": [
        "       ",
        "       ",
        ".^.-.^.",
        "( -,- )",
        "t> - < "
        ],
        "name": "impy",
        "enum": "APPEARANCE_IMP"
    }
]